setup.py
pythondbhelper/__init__.py
pythondbhelper/dbhelper.py
pythondbhelper.egg-info/PKG-INFO
pythondbhelper.egg-info/SOURCES.txt
pythondbhelper.egg-info/dependency_links.txt
pythondbhelper.egg-info/not-zip-safe
pythondbhelper.egg-info/requires.txt
pythondbhelper.egg-info/top_level.txt