Metadata-Version: 1.0
Name: pythondbhelper
Version: 0.1
Summary: python mysql db hlelper class for crud.
Home-page: http://goo.gl/6qM6s7
Author: Waqas Ali
Author-email: waqasali.fastian@gmail.com
License: FAST
Platform: UNKNOWN
